flet_desktop/__init__.py
flet_desktop/version.py
flet_contribe_desktop-2024.12.30.1817.dist-info/METADATA
flet_contribe_desktop-2024.12.30.1817.dist-info/WHEEL
flet_contribe_desktop-2024.12.30.1817.dist-info/RECORD
